{
	"name": "Kode Theme Dark",
	"colors": {
		"activityBar.background": "#3a0ebe5c",
        "activityBar.border": "#7700ff60",
        "activityBar.foreground": "#ffffff",
        "activityBarBadge.background": "#04001030",
        "activityBarBadge.foreground": "#ffffff",
		"badge.background": "#0f013930",
		"breadcrumb.background": "#040010",
		"breadcrumbPicker.background": "#040010",
		"button.background": "#19006350",
		"debugToolBar.background": "#040010",
		"diffEditor.insertedTextBackground": "#00000015",
        "diffEditor.removedTextBackground": "#00000020",
        "dropdown.background": "#040010",
		"editor.background": "#05000a",
		"editorCursor.foreground": "#ff0000",
        "editorError.foreground": "#ff0000",
        "editor.findMatchBackground": "#4000ff",
		"editor.findMatchHighlightBackground": "#c7f65a4d",
		"editor.foreground": "#00ffff",
		"editor.selectionBackground": "#B4B4B430",
		"editor.selectionHighlightBackground": "#1900636b",
		"editorBracketMatch.background": "#040010",
		"editorGroup.border": "#7700ff60",
		"editorGroupHeader.tabsBackground": "#040010",
        "editorGutter.addedBackground": "#00000060",
        "editorGutter.deletedBackground": "#00000060",
        "editorGutter.modifiedBackground": "#B4B4B460",
        "editorHoverWidget.background": "#040010",
		"editorHoverWidget.border": "#00ffff",
		"editorLineNumber.activeForeground": "#00ffff",
        "editorLineNumber.foreground": "#ff0066",
		"editorLink.activeForeground": "#FF0095",
		"editorMarkerNavigation.background": "#ff0095",
		"editorSuggestWidget.selectedBackground": "#19006320",
		"editorSuggestWidget.background": "#ff00f7",
		"extensionButton.prominentBackground": "#00000090",
        "extensionButton.prominentHoverBackground": "#000000",
		"focusBorder": "#ff03a7b7",
		"input.background": "#0D0032",
        "input.border": "#7700ff60",
        "input.foreground": "#ffcfeb",
		"list.activeSelectionBackground": "#040010",
		"menu.background": "#440974f8",
		"menu.border": "#7700ff60",
		"menu.selectionBackground": "#0D0032",
		"menu.separatorBackground": "#00ffff",
        "menubar.selectionBackground": "#0D0032",
		"minimap.background": "#040010",
		"notifications.background": "#040010",
		"panel.background": "#100000",
		"panelTitle.activeBorder": "#7700ff60",
		"peekViewEditor.background": "#ff000005",
		"peekViewTitle.background": "#FF009505",
		"progressBar.background": "#510063",
		"scrollbar.shadow": "#9000ff2a",
        "scrollbarSlider.activeBackground": "#350063cc",
        "scrollbarSlider.background": "#ff00ea3c",
        "scrollbarSlider.hoverBackground": "#1e0340ee",
		"settings.checkboxBackground": "#040010",
		"settings.dropdownBackground": "#040010",
		"sideBarSectionHeader.background": "#380074",
        "sideBarSectionHeader.border": "#00d0ff60",
        "sideBarSectionHeader.foreground": "#ff2c6f",
		"sideBar.background": "#08001e",
		"sideBar.border": "#7700ff60",
		"sideBarTitle.foreground": "#ff94bf",
		"sideBar.foreground": "#ffffff",
		"statusBar.background": "#7806c9",
		"statusBar.border": "#7700ff60",
		"statusBar.foreground": "#ffffff",
		"tab.activeBackground": "#6400a750",
		"tab.activeBorder": "#190063",
        "tab.activeForeground": "#ffffff",
		"tab.border":"#8722fa60",
		"tab.inactiveBackground": "#19006320",
        "tab.inactiveForeground": "#b00067af",
		"terminal.ansiBrightYellow": "#ff00dd",
		"terminalCursor.background": "#00ddff",
        "terminalCursor.foreground": "#00ffff",
		"textLink.activeForeground": "#ffffff",
        "textLink.foreground": "#ffffff",
		"titleBar.activeBackground": "#040010",
        "titleBar.activeForeground": "#ffbee4",
		"titleBar.border": "#7700ff60",
		"titleBar.inactiveBackground": "#040010",
		"titleBar.inactiveForeground": "#b77f9f",
		"tree.indentGuidesStroke": "#120049",
		"toolbar.activeBackground": "#ff0000"
	},
	"tokenColors": [
		{
				"name": "Comment",
				"scope": [
					"comment",
					"punctuation.definition.comment"
				],
				"settings": {
					"fontStyle": "italic",
					"foreground": "#4e4f37"
					}
			},
			
			{
				"name": "Colors",
				"scope": [
					"constant.other.color"
				],
				"settings": {
					"fontStyle": "",
					"foreground": "#ffffff"
				}
			},
			{
				"name": "Invalid",
				"scope": [
					"invalid",
					"invalid.illegal"
				],
				"settings": {
					"foreground": "#FF5370"
				}
			},
			
			
		   
			
			{
				"name": "Eqal",
				"scope": [
					"punctuation",
					"variable.parameter"
				],
				"settings": {
					"fontStyle": "",
					"foreground": "#09ff00"
				}
			},
			
			{
				"name": "Function, Special Method",
				"scope": [
				   
					"meta.function-call",
					"variable.function",
					
					"keyword.other.special-method"
				],
				"settings": {
					"foreground": "#ff7482"
				}
			},
			{
				"name": "Block Level Variables",
				"scope": [
					"meta.block variable.other"
				],
				"settings": {
					"foreground": "#ffffff"
				}
			},
			{
				"name": "Other Variable, String Link",
				"scope": [
					"support.other.variable",
					"string.other.link"
				],
				"settings": {
					"foreground": "#f07178"
				}
			},
			{
				"name": "Number, Constant, Function Argument, Tag Attribute, Embedded",
				"scope": [
				   
					"constant.language",
					"support.constant",
					"constant.character",
					"constant.escape",
				   
				   
					"keyword.other"
				],
				"settings": {
					"foreground": "#ffe1f2"
				}
			},
			{
				"name": "String, Symbols, Inherited Class, Markup Heading",
				"scope": [
					"string",
					"constant.other.symbol",
					"constant.other.key",
					"entity.other.inherited-class",
					"markup.heading",
					"markup.inserted.git_gutter",
					"meta.group.braces.curly constant.other.object.key.js string.unquoted.label.js"
				],
				"settings": {
					"fontStyle": "",
					"foreground": "#c2b4ff"
				}
			},
			{
				"name": "Class, Support",
				"scope": [
					"entity.name",
					"support.type",
					"support.class",
					"support.other.namespace.use.php",
					"meta.use.php",
					"support.other.namespace.php",
					"markup.changed.git_gutter",
					"support.type.sys-types"
				],
				"settings": {
					"foreground": "#FFCB6B"
				}
			},
			{
				"name": "Entity Types",
				"scope": [
					"support.type"
				],
				"settings": {
					"foreground": "#B2CCD6"
				}
			},
			{
				"name": "CSS Class and Support",
				"scope": [
					"source.css support.type.property-name",
					"source.sass support.type.property-name",
					"source.scss support.type.property-name",
					"source.less support.type.property-name",
					"source.stylus support.type.property-name",
					"source.postcss support.type.property-name"
				],
				"settings": {
					"fontStyle": "italic bold",
					"foreground": "#ce63d6"
				}
			},
			{
				"name": "Sub-methods",
				"scope": [
					"entity.name.module.js",
					"variable.import.parameter.js",
					"variable.other.class.js"
				],
				"settings": {
					"foreground": "#FF5370"
				}
			},
			{
				"name": "Language methods",
				"scope": [
					"variable.language"
				],
				"settings": {
					"fontStyle": "italic",
					"foreground": "#FF5370"
				}
			},
			{
				"name": "entity.name.method.js",
				"scope": [
					"entity.name.method.js"
				],
				"settings": {
					"fontStyle": "italic",
					"foreground": "#82AAFF"
				}
			},
			{
				"name": "meta.method.js",
				"scope": [
					"meta.class-method.js entity.name.function.js",
					"variable.function.constructor"
				],
				"settings": {
					"foreground": "#82AAFF"
				}
			},
			
			{
				"name": "HTML Attributes",
				"scope": [
					"text.html.basic entity.other.attribute-name.html",
					"text.html.basic entity.other.attribute-name"
				],
				"settings": {
					"fontStyle": "italic",
					"foreground": "#FFCB6B"
				}
			},
			{
				"name": "CSS Classes",
				"scope": [
					"entity.other.attribute-name.class"
				],
				"settings": {
					"fontStyle": "bold",
					"foreground": "#00ff04"
				}
			},
			{
				"name": "CSS ID's",
				"scope": [
					"source.sass keyword.control"
				],
				"settings": {
					"foreground": "#82AAFF"
				}
			},
			{
				"name": "Inserted",
				"scope": [
					"markup.inserted"
				],
				"settings": {
					"foreground": "#C3E88D"
				}
			},
			{
				"name": "Deleted",
				"scope": [
					"markup.deleted"
				],
				"settings": {
					"foreground": "#FF5370"
				}
			},
			{
				"name": "Changed",
				"scope": [
					"markup.changed"
				],
				"settings": {
					"foreground": "#C792EA"
				}
			},
			{
				"name": "Regular Expressions",
				"scope": [
					"string.regexp"
				],
				"settings": {
					"foreground": "#89DDFF"
				}
			},
			{
				"name": "Escape Characters",
				"scope": [
					"constant.character.escape"
				],
				"settings": {
					"foreground": "#89DDFF"
				}
			},
			{
				"name": "URL",
				"scope": [
					"*url*",
					"*link*",
					"*uri*"
				],
				"settings": {
					"fontStyle": "underline"
				}
			},
			{
				"name": "Decorators",
				"scope": [
					"tag.decorator.js entity.name.tag.js",
					"tag.decorator.js punctuation.definition.tag.js"
				],
				"settings": {
					"fontStyle": "italic",
					"foreground": "#ff0000"
				}
			},
			{
				"name": "ES7 Bind Operator",
				"scope": [
					"source.js constant.other.object.key.js string.unquoted.label.js"
				],
				"settings": {
					"fontStyle": "italic",
					"foreground": "#FF5370"
				}
			},
			{
				"name": "JSON Key - Level 0",
				"scope": [
					"source.json meta.structure.dictionary.json support.type.property-name.json"
				],
				"settings": {
					"foreground": "#C792EA"
				}
			},
			{
				"name": "JSON Key - Level 1",
				"scope": [
					"source.json meta.structure.dictionary.json meta.structure.dictionary.value.json meta.structure.dictionary.json support.type.property-name.json"
				],
				"settings": {
					"foreground": "#FFCB6B"
				}
			},
			{
				"name": "JSON Key - Level 2",
				"scope": [
					"source.json meta.structure.dictionary.json meta.structure.dictionary.value.json meta.structure.dictionary.json meta.structure.dictionary.value.json meta.structure.dictionary.json support.type.property-name.json"
				],
				"settings": {
					"foreground": "#F78C6C"
				}
			},
			{
				"name": "JSON Key - Level 3",
				"scope": [
					"source.json meta.structure.dictionary.json meta.structure.dictionary.value.json meta.structure.dictionary.json meta.structure.dictionary.value.json meta.structure.dictionary.json meta.structure.dictionary.value.json meta.structure.dictionary.json support.type.property-name.json"
				],
				"settings": {
					"foreground": "#FF5370"
				}
			},
			{
				"name": "JSON Key - Level 4",
				"scope": [
					"source.json meta.structure.dictionary.json meta.structure.dictionary.value.json meta.structure.dictionary.json meta.structure.dictionary.value.json meta.structure.dictionary.json meta.structure.dictionary.value.json meta.structure.dictionary.json meta.structure.dictionary.value.json meta.structure.dictionary.json support.type.property-name.json"
				],
				"settings": {
					"foreground": "#C17E70"
				}
			},
			{
				"name": "JSON Key - Level 5",
				"scope": [
					"source.json meta.structure.dictionary.json meta.structure.dictionary.value.json meta.structure.dictionary.json meta.structure.dictionary.value.json meta.structure.dictionary.json meta.structure.dictionary.value.json meta.structure.dictionary.json meta.structure.dictionary.value.json meta.structure.dictionary.json meta.structure.dictionary.value.json meta.structure.dictionary.json support.type.property-name.json"
				],
				"settings": {
					"foreground": "#82AAFF"
				}
			},
			{
				"name": "JSON Key - Level 6",
				"scope": [
					"source.json meta.structure.dictionary.json meta.structure.dictionary.value.json meta.structure.dictionary.json meta.structure.dictionary.value.json meta.structure.dictionary.json meta.structure.dictionary.value.json meta.structure.dictionary.json meta.structure.dictionary.value.json meta.structure.dictionary.json meta.structure.dictionary.value.json meta.structure.dictionary.json meta.structure.dictionary.value.json meta.structure.dictionary.json support.type.property-name.json"
				],
				"settings": {
					"foreground": "#f07178"
				}
			},
			{
				"name": "JSON Key - Level 7",
				"scope": [
					"source.json meta.structure.dictionary.json meta.structure.dictionary.value.json meta.structure.dictionary.json meta.structure.dictionary.value.json meta.structure.dictionary.json meta.structure.dictionary.value.json meta.structure.dictionary.json meta.structure.dictionary.value.json meta.structure.dictionary.json meta.structure.dictionary.value.json meta.structure.dictionary.json meta.structure.dictionary.value.json meta.structure.dictionary.json meta.structure.dictionary.value.json meta.structure.dictionary.json support.type.property-name.json"
				],
				"settings": {
					"foreground": "#C792EA"
				}
			},
			{
				"name": "JSON Key - Level 8",
				"scope": [
					"source.json meta.structure.dictionary.json meta.structure.dictionary.value.json meta.structure.dictionary.json meta.structure.dictionary.value.json meta.structure.dictionary.json meta.structure.dictionary.value.json meta.structure.dictionary.json meta.structure.dictionary.value.json meta.structure.dictionary.json meta.structure.dictionary.value.json meta.structure.dictionary.json meta.structure.dictionary.value.json meta.structure.dictionary.json meta.structure.dictionary.value.json meta.structure.dictionary.json meta.structure.dictionary.value.json meta.structure.dictionary.json support.type.property-name.json"
				],
				"settings": {
					"foreground": "#C3E88D"
				}
			},
			{
				"name": "Markdown - Plain",
				"scope": [
					"text.html.markdown",
					"punctuation.definition.list_item.markdown"
				],
				"settings": {
					"foreground": "#EEFFFF"
				}
			},
			{
				"name": "Markdown - Markup Raw Inline",
				"scope": [
					"text.html.markdown markup.inline.raw.markdown"
				],
				"settings": {
					"foreground": "#C792EA"
				}
			},
			{
				"name": "Markdown - Markup Raw Inline Punctuation",
				"scope": [
					"text.html.markdown markup.inline.raw.markdown punctuation.definition.raw.markdown"
				],
				"settings": {
					"foreground": "#65737E"
				}
			},
			{
				"name": "Markdown - Heading",
				"scope": [
					"markdown.heading",
					"markup.heading | markup.heading entity.name",
					"markup.heading.markdown punctuation.definition.heading.markdown"
				],
				"settings": {
					"foreground": "#C3E88D"
				}
			},
			{
				"name": "Markup - Italic",
				"scope": [
					"markup.italic"
				],
				"settings": {
					"fontStyle": "italic",
					"foreground": "#f07178"
				}
			},
			{
				"name": "Markup - Bold",
				"scope": [
					"markup.bold",
					"markup.bold string"
				],
				"settings": {
					"fontStyle": "bold",
					"foreground": "#f07178"
				}
			},
			{
				"name": "Markup - Bold-Italic",
				"scope": [
					"markup.bold markup.italic",
					"markup.italic markup.bold",
					"markup.quote markup.bold",
					"markup.bold markup.italic string",
					"markup.italic markup.bold string",
					"markup.quote markup.bold string"
				],
				"settings": {
					"fontStyle": "bold",
					"foreground": "#f07178"
				}
			},
			{
				"name": "Markup - Underline",
				"scope": [
					"markup.underline"
				],
				"settings": {
					"fontStyle": "underline",
					"foreground": "#F78C6C"
				}
			},
			{
				"name": "Markdown - Blockquote",
				"scope": [
					"markup.quote punctuation.definition.blockquote.markdown"
				],
				"settings": {
					"foreground": "#65737E"
				}
			},
			{
				"name": "Markup - Quote",
				"scope": [
					"markup.quote"
				],
				"settings": {
					"fontStyle": "italic"
				}
			},
			{
				"name": "Markdown - Link",
				"scope": [
					"string.other.link.title.markdown"
				],
				"settings": {
					"foreground": "#82AAFF"
				}
			},
			{
				"name": "Markdown - Link Description",
				"scope": [
					"string.other.link.description.title.markdown"
				],
				"settings": {
					"foreground": "#C792EA"
				}
			},
			{
				"name": "Markdown - Link Anchor",
				"scope": [
					"constant.other.reference.link.markdown"
				],
				"settings": {
					"foreground": "#FFCB6B"
				}
			},
			{
				"name": "Markup - Raw Block",
				"scope": [
					"markup.raw.block"
				],
				"settings": {
					"foreground": "#C792EA"
				}
			},
			{
				"name": "Markdown - Raw Block Fenced",
				"scope": [
					"markup.raw.block.fenced.markdown"
				],
				"settings": {
					"foreground": "#ff000050"
				}
			},
			{
				"name": "Markdown - Fenced Bode Block",
				"scope": [
					"punctuation.definition.fenced.markdown"
				],
				"settings": {
					"foreground": "#00000050"
				}
			},
			{
				"name": "Markdown - Fenced Bode Block Variable",
				"scope": [
					"markup.raw.block.fenced.markdown",
					"variable.language.fenced.markdown",
					"punctuation.section.class.end"
				],
				"settings": {
					"foreground": "#EEFFFF"
				}
			},
			{
				"name": "Markdown - Fenced Language",
				"scope": [
					"variable.language.fenced.markdown"
				],
				"settings": {
					"foreground": "#65737E"
				}
			},
			{
				"name": "Markdown - Separator",
				"scope": [
					"meta.separator"
				],
				"settings": {
					"fontStyle": "bold",
					"foreground": "#65737E"
				}
			},
			{
				"name": "Markup - Table",
				"scope": [
					"markup.table"
				],
				"settings": {
					"foreground": "#EEFFFF"
				}
			},
			// ADDED BY ME FOR JS
			
			
			{
				"name": "Javascript function definition",
				"scope": [
					"storage.type.function"

				],
				"settings": {
					"fontStyle": "",
					"foreground": "#ff0000"
				}
			},
			
			{
				"name": "Javascript brackets name",
				"scope": [
					"meta.function.expression.js",
					"support.variable.property.js",
				],
				"settings": {
					"fontStyle": "",
					"foreground": "#00ff00"
				}
			},
			
			
			
			
			




			// HTML
			{
				"name": "Tag",
				"scope": [
					"entity.name.tag.html",
					"meta.tag.sgml",
					"markup.deleted.git_gutter",
				],
				"settings": {
					"fontStyle": "",
					// "foreground": "#ff481f"
					"foreground": "#ff8c00"
				}
			},
			{
				"name": "Tag",
				"scope": [
					"punctuation.separator.key-value.html",
				],
				"settings": {
					"fontStyle": "",
					"foreground": "#ff2e96"
				}
			},
			{
				"name": "html clases",
				"scope": [
					"punctuation.definition.string.begin.html",
					"punctuation.definition.string.end.html",
					"string.quoted.double.html",
				],
				"settings": {
					"fontStyle": "",
					// "foreground": "#00c3ff"
					"foreground": "#51f6a9"
				}
			},
			{
				"name": "Attributes",
				"scope": [
					"entity.other.attribute-name"
				],
				"settings": {
					"fontStyle": "italic",
					"foreground": "#7a5cff"
				}
			},
			{
				"name": "Operator, Misc",
				"scope": [
					"constant.other.color",
					"meta.tag",
					"punctuation.definition.tag",
					"punctuation.separator.inheritance.php",
					"punctuation.definition.tag.html",
					"punctuation.definition.tag.begin.html",
					"punctuation.definition.tag.end.html",
					"punctuation.section.embedded",
					
					"keyword.other.template",
					"keyword.other.substitution"
				],
				"settings": {
					"fontStyle": "bold",
					"foreground": "#d84164"
					// "foreground": "#b9fff1"
				}
			},
			{
				"name": " html content",
				"scope": [
					"text.html.derivative",
				],
				"settings": {
					"fontStyle": "italic",
					"foreground": "#ffffff"
				}
			},





			// CSS
			{
				"name": "css class and punctuation",
				"scope": [
					"punctuation.separator.key-value.css",
					"entity.name.tag.wildcard.css",
					
					"keyword.control.at-rule.import.css",
					"punctuation.definition.string.begin.css",
					"punctuation.definition.string.end.css",
					"punctuation.separator.list.comma.css",
					"entity.other.attribute-name.class",
					"entity.other.attribute-name.id.css",
				],
				"settings": {
					"fontStyle": "bold",
					"foreground": "#ff00d9"
				}
			},
			{
				"name": "css properties",
				"scope": [
					"support.type.property-name.css",
					
					
					"support.function.url.css"
				],
				"settings": {
					"fontStyle": "",
					"foreground": "#aa7dff"
				}
			},
			{
				"name": "css properties",
				"scope": [
					"punctuation.separator.key-value.css",
					"punctuation.terminator.rule.css",
					"punctuation.definition.entity.css",
					"punctuation.definition.keyword.css",
					"meta.property-list.css",
					"source.css",
					"support.function",
				],
				"settings": {
					"fontStyle": "",
					"foreground": "#ffaa00"
				
				}
			},
			{
				"name": "css properties",
				"scope": [
					"constant.numeric.css",
					"keyword.other.unit",
					"keyword.other.unit.percentage.css",
				],
				"settings": {
					"fontStyle": "",
					"foreground": "#2bff00"
				
				}
			},
			{
				"name": "css properties",
				"scope": [
					"support.function.transform.css",
				],
				"settings": {
					"fontStyle": "italic",
					"foreground": "#ffaa00"
				
				}
			},
			{
				"name": "css properties",
				"scope": [
					"entity.name.tag.css",
				],
				"settings": {
					"fontStyle": "bold",
					"foreground": "#51f6a9"
				
				}
			},




			// javaScript
			{
				"name": " Storage",
				"scope": [
					"storage.type",
					"storage.modifier",
					"punctuation.accessor.js",
					
				],
				"settings": {
					"fontStyle": "italic",
					"foreground": "#00c3ff"
				}
			},
			{
				"name": "Javascript Operator",
				"scope": [
					"keyword.operator.arithmetic.js",
					"keyword.operator.assignment.js",
					"keyword.operator.relational.js",
					"keyword.operator.increment.js",
					"storage.type.function.arrow.js",
					"keyword.operator.comparison.js",
					"keyword.operator.expression.of.js"
					
					
				],
				"settings": {
					"fontStyle": "bold",
					"foreground": "#ff2e2e"
				}
			},
			{
				"name": "Javascript comma",
				"scope": [
					"punctuation.separator.comma.js",
					"punctuation.terminator.statement.js",
				],
				"settings": {
					"fontStyle": "",
					"foreground": "#ffffff"
				}
			},
			{
				"name": "Javascript keys symbols",
				"scope": [
					"keyword",
					"punctuation.definition.string.begin.js",
					"punctuation.definition.string.end.js",
					"punctuation.definition.string.template.begin.js",
					"punctuation.definition.string.template.end.js",
					"string.template.js",
					"string.quoted.single.js",
					"string.quoted.double.js",
					"meta.brace.round.js",
					
				],
				"settings": {
					"fontStyle": "",
					"foreground": "#ff8c00"
				}
			},
			{
				"name": "Javascript keys symbols",
				"scope": [
					
					"constant.numeric",
					
				],
				"settings": {
					"fontStyle": "",
					"foreground": "#2bff00"
				}
			},
			{
				"name": "Javascript loop",
				"scope": [
					"keyword.control",
					"punctuation.definition.block.js",
					"punctuation.definition.parameters.begin.js",
					
					"punctuation.definition.template-expression.begin.js",
					"punctuation.definition.template-expression.end.js",
				],
				"settings": {
					"fontStyle": "bold",
					"foreground": "#ff00d9"
				}
			},
			{
				"name": "Javascript function name",
				"scope": [
					"entity.name.function.js",
				],
				"settings": {
					"fontStyle": "italic",
					"foreground": "#d84164"
				}
			},
			{
				"name": "Javascript variable parameter",
				"scope": [
					"variable.parameter.js",
				],
				"settings": {
					"fontStyle": "italic",
					"foreground": "#ee00ff"
				}
			},
			{
				"name": "Javascript variable parameter",
				"scope": [
					"variable.other.object.js"
				],
				"settings": {
					"fontStyle": "italic",
					"foreground": "#51f6a9"
				}
			},
			{
				"name": "Variables",
				"scope": [
					"variable",
					"string constant.other.placeholder",
					"meta.block variable.other",
				],
				"settings": {
					"foreground": "#b9fff1"
				}
			},
			
		]
	}
	
	
	
	
	
	
	
	
	
	
	
	
	
	
	
	